{
    "language-name": "한글",
    "toolbar": {
        "run": "전체 코드 실행 (ctrl+shift+enter)",
        "upload": "갤러리에 업로드 하기",
        "clear": "모두 지우기",
        "shuffle": "무작위 스케치 보기",
        "random": "무작위로 코드 바꾸기",
        "show-info": "인포 윈도우 표시",
        "hide-info": "인포 윈도우 감추기"
    },
    "info": {
        "title": "하이드라",
        "subtitle": "라이브 코딩 비디오 신스",
        "description": "하이드라는 브라우저에서 직접 실행되는 라이브 코딩 비디오 신스 및 코딩 환경입니다. 무료, 오픈 소스이며 초보자와 전문가 모두를 위해 제작되었습니다.",
        "get-started-title": "시작하려면:",
        "get-started-list": [
            "현재 보고 있는 이 창을 닫고",
            "코드에 있는 숫자를 바꿔보세요.",
            "그 후에 Ctrl + Shift + Enter 를 눌러보세요."
        ],
        "description-detailed": "하이드라는 자바스크립트로 작성되었으며 내부적으로는 WebGL로 컴파일됩니다. 하이드라의 문법은 아날로그 모듈러 신디사이저에서 영감을 받았으며, 일련의 변환을 연결하거나 조정하면 그에 따른 시각적 결과가 생성됩니다.",
        "uses": "하이드라는 다음과 같은 용도로 사용될 수 있습니다:",
        "uses-list": [
            "카메라 피드, 스크린 셰어, 라이브 스트림 및 비디오에 시각 효과를 믹스하거나 추가할 수 있습니다.",
            "실시간으로 생성되며 오디오에 반응하는 비주얼을 만들고 이를 다른 사람들과 공유할 수 있습니다.",
            "P5.js, Tone.js, THREE.js, gibber와 같은 다른 자바스크립트 라이브러리와 함께 사용할 수 있습니다.",
            "웹사이트에 익터랙티브한 비디오를 추가할 수 있습니다.",
            "비디오 피드백, 프랙탈, 그리고 픽셀 연산에 관한 실험을 하고 이를 배울 수 있습니다.",
            "비디오를 브라우저 간에 스트리밍하고 온라인에서 다른 사람들과 실시간으로 잼을 할 수 있습니다."
        ],
        "author": "제작자 <a {{author}}>olivia.</a>",
        "more-info": "더 자세한 사항은 이곳을 참조하세요: <a {{docs}}>인터랙티브한 문서</a>, <a {{functions}}>하이드라 함수들</a>, <a {{garden}}>커뮤니티 기반의 프로젝트와 튜토리얼</a>, <a {{gallery}}>유저들이 작성한 스케치들</a>, 그리고 <a {{repo}}>소스코드(깃허브)</a>,",
        "more-info-forums": "또한, 하이드라 유저들과 기여자들을 위한 <a {{discord}}>디스코드 서버</a>와 <a {{facebook}}>페이스북 그룹</a>도 있습니다.",
        "support": "만약 하이드라를 잘 사용하고 계신다면  <a {{open-collective}} >지속적인 개발을 위한 후원도 고려해주세요<3 </a>."
    }
}